{
  "title": "Lolroms-genesis",
  "description": "LolRoms hosted Sega Mega Drive",
  "download": [
    {
      "title": "007 Shitou - The Duel (Japan) (En)",
      "uris": [
        "https://lolroms.com/SEGA/Mega%20Drive/007%20Shitou%20-%20The%20Duel%20%28Japan%29%20%28En%29.7z"
      ],
      "uploadDate": "2026-03-12",
      "console": "genesis"
    },
    {
      "title": "10 Super Jogos (Brazil) (En)",
      "uris": [
        "https://lolroms.com/SEGA/Mega%20Drive/10%20Super%20Jogos%20%28Brazil%29%20%28En%29.7z"
      ],
      "uploadDate": "2026-03-12",
      "console": "genesis"
    },
    {
      "title": "14-in-1 (Taiwan) (En) (Aftermarket) (Pirate)",
      "uris": [
        "https://lolroms.com/SEGA/Mega%20Drive/14-in-1%20%28Taiwan%29%20%28En%29%20%28Aftermarket%29%20%28Pirate%29.7z"
      ],
      "uploadDate": "2026-03-12",
      "console": "genesis"
    },
    {
      "title": "16Bit Rhythm Land (Japan) (En) (Aftermarket) (Unl)",
      "uris": [
        "https://lolroms.com/SEGA/Mega%20Drive/16Bit%20Rhythm%20Land%20%28Japan%29%20%28En%29%20%28Aftermarket%29%20%28Unl%29.7z"
      ],
      "uploadDate": "2026-03-12",
      "console": "genesis"
    },
    {
      "title": "16t (Japan) (Game no Kanzume Otokuyou)",
      "uris": [
        "https://lolroms.com/SEGA/Mega%20Drive/16t%20%28Japan%29%20%28Game%20no%20Kanzume%20Otokuyou%29.7z"
      ],
      "uploadDate": "2026-03-12",
      "console": "genesis"
    },
    {
      "title": "16t (Japan) (Game no Kanzume Vol. 2) [b]",
      "uris": [
        "https://lolroms.com/SEGA/Mega%20Drive/16t%20%28Japan%29%20%28Game%20no%20Kanzume%20Vol.%202%29%20%5Bb%5D.7z"
      ],
      "uploadDate": "2026-03-12",
      "console": "genesis"
    },
    {
      "title": "16t (Japan) (Sega Game Toshokan)",
      "uris": [
        "https://lolroms.com/SEGA/Mega%20Drive/16t%20%28Japan%29%20%28Sega%20Game%20Toshokan%29.7z"
      ],
      "uploadDate": "2026-03-12",
      "console": "genesis"
    },
    {
      "title": "2 Ciclopes and Friends - The Fight Game (World) (Pt) (Beta) (Aftermarket) (Unl)",
      "uris": [
        "https://lolroms.com/SEGA/Mega%20Drive/2%20Ciclopes%20and%20Friends%20-%20The%20Fight%20Game%20%28World%29%20%28Pt%29%20%28Beta%29%20%28Aftermarket%29%20%28Unl%29.7z"
      ],
      "uploadDate": "2026-03-12",
      "console": "genesis"
    },
    {
      "title": "2 Ciclopes and Friends - The Fight Game - Winner Edition (World) (Pt) (Aftermarket) (Unl)",
      "uris": [
        "https://lolroms.com/SEGA/Mega%20Drive/2%20Ciclopes%20and%20Friends%20-%20The%20Fight%20Game%20-%20Winner%20Edition%20%28World%29%20%28Pt%29%20%28Aftermarket%29%20%28Unl%29.7z"
      ],
      "uploadDate": "2026-03-12",
      "console": "genesis"
    },
    {
      "title": "2 Ciclopes e Amigos - Fight Game - Winner Edition - New Challengers (World) (Pt) (Aftermarket) (Unl)",
      "uris": [
        "https://lolroms.com/SEGA/Mega%20Drive/2%20Ciclopes%20e%20Amigos%20-%20Fight%20Game%20-%20Winner%20Edition%20-%20New%20Challengers%20%28World%29%20%28Pt%29%20%28Aftermarket%29%20%28Unl%29.7z"
      ],
      "uploadDate": "2026-03-12",
      "console": "genesis"
    },
    {
      "title": "2020 Nen Super Baseball (Japan)",
      "uris": [
        "https://lolroms.com/SEGA/Mega%20Drive/2020%20Nen%20Super%20Baseball%20%28Japan%29.7z"
      ],
      "uploadDate": "2026-03-12",
      "console": "genesis"
    },
    {
      "title": "240p Test Suite (World) (v1.23) (Emu) (Program) (Aftermarket) (Unl)",
      "uris": [
        "https://lolroms.com/SEGA/Mega%20Drive/240p%20Test%20Suite%20%28World%29%20%28v1.23%29%20%28Emu%29%20%28Program%29%20%28Aftermarket%29%20%28Unl%29.7z"
      ],
      "uploadDate": "2026-03-12",
      "console": "genesis"
    },
    {
      "title": "240p Test Suite (World) (v1.23) (Program) (Aftermarket) (Unl)",
      "uris": [
        "https://lolroms.com/SEGA/Mega%20Drive/240p%20Test%20Suite%20%28World%29%20%28v1.23%29%20%28Program%29%20%28Aftermarket%29%20%28Unl%29.7z"
      ],
      "uploadDate": "2026-03-12",
      "console": "genesis"
    },
    {
      "title": "240p Test Suite (World) (v1.30) (Emu) (Program) (Aftermarket) (Unl)",
      "uris": [
        "https://lolroms.com/SEGA/Mega%20Drive/240p%20Test%20Suite%20%28World%29%20%28v1.30%29%20%28Emu%29%20%28Program%29%20%28Aftermarket%29%20%28Unl%29.7z"
      ],
      "uploadDate": "2026-03-12",
      "console": "genesis"
    },
    {
      "title": "240p Test Suite (World) (v1.30) (Program) (Aftermarket) (Unl)",
      "uris": [
        "https://lolroms.com/SEGA/Mega%20Drive/240p%20Test%20Suite%20%28World%29%20%28v1.30%29%20%28Program%29%20%28Aftermarket%29%20%28Unl%29.7z"
      ],
      "uploadDate": "2026-03-12",
      "console": "genesis"
    },
    {
      "title": "240p Test Suite (World) (v1.31) (Emu) (Program) (Aftermarket) (Unl)",
      "uris": [
        "https://lolroms.com/SEGA/Mega%20Drive/240p%20Test%20Suite%20%28World%29%20%28v1.31%29%20%28Emu%29%20%28Program%29%20%28Aftermarket%29%20%28Unl%29.7z"
      ],
      "uploadDate": "2026-03-12",
      "console": "genesis"
    },
    {
      "title": "240p Test Suite (World) (v1.31) (Program) (Aftermarket) (Unl)",
      "uris": [
        "https://lolroms.com/SEGA/Mega%20Drive/240p%20Test%20Suite%20%28World%29%20%28v1.31%29%20%28Program%29%20%28Aftermarket%29%20%28Unl%29.7z"
      ],
      "uploadDate": "2026-03-12",
      "console": "genesis"
    },
    {
      "title": "3 Block Match (World) (Aftermarket) (Unl)",
      "uris": [
        "https://lolroms.com/SEGA/Mega%20Drive/3%20Block%20Match%20%28World%29%20%28Aftermarket%29%20%28Unl%29.7z"
      ],
      "uploadDate": "2026-03-12",
      "console": "genesis"
    },
    {
      "title": "3 Block Match (World) (v1.1) (Aftermarket) (Unl)",
      "uris": [
        "https://lolroms.com/SEGA/Mega%20Drive/3%20Block%20Match%20%28World%29%20%28v1.1%29%20%28Aftermarket%29%20%28Unl%29.7z"
      ],
      "uploadDate": "2026-03-12",
      "console": "genesis"
    },
    {
      "title": "3 Ninjas Kick Back (USA)",
      "uris": [
        "https://lolroms.com/SEGA/Mega%20Drive/3%20Ninjas%20Kick%20Back%20%28USA%29.7z"
      ],
      "uploadDate": "2026-03-12",
      "console": "genesis"
    }
  ]
}